markowitz_portfolio_optimizer/__init__.py
markowitz_portfolio_optimizer/calc_utils.py
markowitz_portfolio_optimizer/data_utils.py
markowitz_portfolio_optimizer/data/example_dataset.csv
markowitz_portfolio_optimizer-1.27.dist-info/licenses/LICENSE
markowitz_portfolio_optimizer-1.27.dist-info/METADATA
markowitz_portfolio_optimizer-1.27.dist-info/WHEEL
markowitz_portfolio_optimizer-1.27.dist-info/top_level.txt
markowitz_portfolio_optimizer-1.27.dist-info/RECORD
