Metadata-Version: 2.4
Name: markowitz_portfolio_optimizer
Version: 1.27
Summary: Optimize you portfolio!
Author-email: SZD <sziklaidominik09@gmail.com>
Maintainer-email: GK <gatmezei.kornel@gmail.com>
License-Expression: GPL-3.0-only
Project-URL: Homepage, https://github.com/SirArthur100
Project-URL: Documentation, https://portfolio-optimizer.readthedocs.io/en/latest/
Project-URL: Repository, https://github.com/SirArthur100/scientific_python
Project-URL: Issues, https://github.com/SirArthur100/scientific_python/issues
Classifier: Development Status :: 1 - Planning
Classifier: Programming Language :: Python :: 3.10
Classifier: Operating System :: OS Independent
Requires-Python: >=3.10
License-File: LICENSE
Requires-Dist: numpy==1.26.3
Requires-Dist: pandas==2.1.4
Requires-Dist: matplotlib==3.8.1
Requires-Dist: scipy==1.11.4
Requires-Dist: sphinx-rtd-theme==3.0.2
Dynamic: license-file
